{
   "destination_addresses" : [
      "8480 Castleton Corner Dr, Indianapolis, IN 46250, USA",
      "7513 Northcrest Dr, Indianapolis, IN 46256, USA",
      "9507 E 86th St, Indianapolis, IN 46256, USA",
      "8409 Carefree Cir, Indianapolis, IN 46236, USA",
      "6415 W Cedar Chase Dr, McCordsville, IN 46055, USA",
      "10581 Hazel Dell Pkwy, Indianapolis, IN 46033, USA",
      "Beech Hollow Trail Loop, Indianapolis, IN 46256, USA",
      "10580 Cumberland Rd, Fishers, IN 46037, USA",
      "11422 Governors Ln, Fishers, IN 46037, USA",
      "13579 Marjac Way, McCordsville, IN 46055, USA",
      "5724 Pebblestone Ct, Carmel, IN 46033, USA",
      "River Highlands, 12500 Kelly Pl, Fishers, IN 46038, USA",
      "12201 Reynolds Dr, Fishers, IN 46038, USA",
      "12354 Hoosier Rd, Fishers, IN 46037, USA",
      "13251 Duval Dr, Fishers, IN 46037, USA",
      "14460 Bexley Dr, Carmel, IN 46033, USA",
      "14550 River Rd, Carmel, IN 46033, USA",
      "14295 Mourning Dove Ln, Noblesville, IN 46060, USA",
      "11260 E 141st St, Noblesville, IN 46060, USA"
   ],
   "origin_addresses" : [ "4 Municipal Dr, Fishers, IN 46038, USA" ],
   "rows" : [
      {
         "elements" : [
            {
               "distance" : {
                  "text" : "5.5 mi",
                  "value" : 8846
               },
               "duration" : {
                  "text" : "13 mins",
                  "value" : 779
               },
               "status" : "OK"
            },
            {
               "distance" : {
                  "text" : "4.8 mi",
                  "value" : 7800
               },
               "duration" : {
                  "text" : "11 mins",
                  "value" : 649
               },
               "status" : "OK"
            },
            {
               "distance" : {
                  "text" : "5.0 mi",
                  "value" : 8095
               },
               "duration" : {
                  "text" : "12 mins",
                  "value" : 744
               },
               "status" : "OK"
            },
            {
               "distance" : {
                  "text" : "9.9 mi",
                  "value" : 15880
               },
               "duration" : {
                  "text" : "20 mins",
                  "value" : 1217
               },
               "status" : "OK"
            },
            {
               "distance" : {
                  "text" : "8.6 mi",
                  "value" : 13778
               },
               "duration" : {
                  "text" : "17 mins",
                  "value" : 1038
               },
               "status" : "OK"
            },
            {
               "distance" : {
                  "text" : "5.6 mi",
                  "value" : 8943
               },
               "duration" : {
                  "text" : "11 mins",
                  "value" : 677
               },
               "status" : "OK"
            },
            {
               "distance" : {
                  "text" : "2.5 mi",
                  "value" : 3987
               },
               "duration" : {
                  "text" : "6 mins",
                  "value" : 389
               },
               "status" : "OK"
            },
            {
               "distance" : {
                  "text" : "2.9 mi",
                  "value" : 4669
               },
               "duration" : {
                  "text" : "9 mins",
                  "value" : 551
               },
               "status" : "OK"
            },
            {
               "distance" : {
                  "text" : "4.3 mi",
                  "value" : 6981
               },
               "duration" : {
                  "text" : "11 mins",
                  "value" : 643
               },
               "status" : "OK"
            },
            {
               "distance" : {
                  "text" : "7.4 mi",
                  "value" : 11885
               },
               "duration" : {
                  "text" : "16 mins",
                  "value" : 937
               },
               "status" : "OK"
            },
            {
               "distance" : {
                  "text" : "4.4 mi",
                  "value" : 7058
               },
               "duration" : {
                  "text" : "10 mins",
                  "value" : 599
               },
               "status" : "OK"
            },
            {
               "distance" : {
                  "text" : "2.2 mi",
                  "value" : 3534
               },
               "duration" : {
                  "text" : "6 mins",
                  "value" : 347
               },
               "status" : "OK"
            },
            {
               "distance" : {
                  "text" : "2.1 mi",
                  "value" : 3431
               },
               "duration" : {
                  "text" : "7 mins",
                  "value" : 411
               },
               "status" : "OK"
            },
            {
               "distance" : {
                  "text" : "3.8 mi",
                  "value" : 6185
               },
               "duration" : {
                  "text" : "10 mins",
                  "value" : 574
               },
               "status" : "OK"
            },
            {
               "distance" : {
                  "text" : "6.0 mi",
                  "value" : 9617
               },
               "duration" : {
                  "text" : "13 mins",
                  "value" : 753
               },
               "status" : "OK"
            },
            {
               "distance" : {
                  "text" : "6.3 mi",
                  "value" : 10151
               },
               "duration" : {
                  "text" : "13 mins",
                  "value" : 802
               },
               "status" : "OK"
            },
            {
               "distance" : {
                  "text" : "5.2 mi",
                  "value" : 8312
               },
               "duration" : {
                  "text" : "12 mins",
                  "value" : 718
               },
               "status" : "OK"
            },
            {
               "distance" : {
                  "text" : "3.6 mi",
                  "value" : 5763
               },
               "duration" : {
                  "text" : "9 mins",
                  "value" : 553
               },
               "status" : "OK"
            },
            {
               "distance" : {
                  "text" : "5.3 mi",
                  "value" : 8502
               },
               "duration" : {
                  "text" : "12 mins",
                  "value" : 705
               },
               "status" : "OK"
            }
         ]
      }
   ],
   "status" : "OK"
}
