{
   "destination_addresses" : [
      "8709 W County Rd 550 S, Daleville, IN 47334, USA",
      "9698-8912 S Country Rd 300 W, Muncie, IN 47302, USA",
      "9698-8400 S Co Rd 100 W, Muncie, IN 47302, USA",
      "101-911 E Co Rd 578 S, Muncie, IN 47302, USA",
      "4081 E Co Rd 550 S, Muncie, IN 47302, USA",
      "7101 E Co Rd 550 S, Muncie, IN 47302, USA",
      "4901-6499 S 550 W Rd, Yorktown, IN 47396, USA",
      "5701 S Co Rd 325 W, Muncie, IN 47302, USA",
      "Muncie Bypass, Muncie, IN 47302, USA",
      "5750 S Walnut St, Muncie, IN 47302, USA",
      "3855 E Co Rd 350 S, Muncie, IN 47302, USA",
      "5701 S 475 E Rd, Selma, IN 47383, USA",
      "8520 W Cornbread Rd, Yorktown, IN 47396, USA",
      "5670 W Cornbread Rd, Yorktown, IN 47396, USA",
      "2101 W Cornbread Rd, Muncie, IN 47302, USA",
      "921 E 20th St, Muncie, IN 47302, USA",
      "4301 E Maple Manor Pkwy, Muncie, IN 47302, USA",
      "7305 E Smithfield Pike, Muncie, IN 47302, USA",
      "8604 W Tulip Tree Dr, Muncie, IN 47304, USA",
      "Deerbrook, 5508 W Autumn Springs Ct, Muncie, IN 47304, USA",
      "Central Chilling Plant, 2306 W University Ave, Muncie, IN 47306, USA",
      "E McCulloch Blvd, Muncie, IN 47303, USA"
   ],
   "origin_addresses" : [ "620 S Mulberry St, Muncie, IN 47305, USA" ],
   "rows" : [
      {
         "elements" : [
            {
               "distance" : {
                  "text" : "8.6 mi",
                  "value" : 13762
               },
               "duration" : {
                  "text" : "15 mins",
                  "value" : 924
               },
               "status" : "OK"
            },
            {
               "distance" : {
                  "text" : "7.1 mi",
                  "value" : 11377
               },
               "duration" : {
                  "text" : "15 mins",
                  "value" : 871
               },
               "status" : "OK"
            },
            {
               "distance" : {
                  "text" : "6.6 mi",
                  "value" : 10557
               },
               "duration" : {
                  "text" : "14 mins",
                  "value" : 829
               },
               "status" : "OK"
            },
            {
               "distance" : {
                  "text" : "6.3 mi",
                  "value" : 10209
               },
               "duration" : {
                  "text" : "12 mins",
                  "value" : 718
               },
               "status" : "OK"
            },
            {
               "distance" : {
                  "text" : "8.5 mi",
                  "value" : 13610
               },
               "duration" : {
                  "text" : "15 mins",
                  "value" : 906
               },
               "status" : "OK"
            },
            {
               "distance" : {
                  "text" : "8.5 mi",
                  "value" : 13747
               },
               "duration" : {
                  "text" : "15 mins",
                  "value" : 924
               },
               "status" : "OK"
            },
            {
               "distance" : {
                  "text" : "8.5 mi",
                  "value" : 13713
               },
               "duration" : {
                  "text" : "17 mins",
                  "value" : 990
               },
               "status" : "OK"
            },
            {
               "distance" : {
                  "text" : "5.6 mi",
                  "value" : 9008
               },
               "duration" : {
                  "text" : "13 mins",
                  "value" : 793
               },
               "status" : "OK"
            },
            {
               "distance" : {
                  "text" : "6.1 mi",
                  "value" : 9853
               },
               "duration" : {
                  "text" : "13 mins",
                  "value" : 796
               },
               "status" : "OK"
            },
            {
               "distance" : {
                  "text" : "3.8 mi",
                  "value" : 6040
               },
               "duration" : {
                  "text" : "9 mins",
                  "value" : 518
               },
               "status" : "OK"
            },
            {
               "distance" : {
                  "text" : "5.4 mi",
                  "value" : 8611
               },
               "duration" : {
                  "text" : "11 mins",
                  "value" : 672
               },
               "status" : "OK"
            },
            {
               "distance" : {
                  "text" : "7.4 mi",
                  "value" : 11947
               },
               "duration" : {
                  "text" : "15 mins",
                  "value" : 913
               },
               "status" : "OK"
            },
            {
               "distance" : {
                  "text" : "6.5 mi",
                  "value" : 10445
               },
               "duration" : {
                  "text" : "15 mins",
                  "value" : 900
               },
               "status" : "OK"
            },
            {
               "distance" : {
                  "text" : "4.5 mi",
                  "value" : 7308
               },
               "duration" : {
                  "text" : "11 mins",
                  "value" : 687
               },
               "status" : "OK"
            },
            {
               "distance" : {
                  "text" : "2.6 mi",
                  "value" : 4185
               },
               "duration" : {
                  "text" : "8 mins",
                  "value" : 473
               },
               "status" : "OK"
            },
            {
               "distance" : {
                  "text" : "1.9 mi",
                  "value" : 3113
               },
               "duration" : {
                  "text" : "6 mins",
                  "value" : 336
               },
               "status" : "OK"
            },
            {
               "distance" : {
                  "text" : "4.0 mi",
                  "value" : 6498
               },
               "duration" : {
                  "text" : "10 mins",
                  "value" : 580
               },
               "status" : "OK"
            },
            {
               "distance" : {
                  "text" : "6.2 mi",
                  "value" : 10002
               },
               "duration" : {
                  "text" : "12 mins",
                  "value" : 708
               },
               "status" : "OK"
            },
            {
               "distance" : {
                  "text" : "7.0 mi",
                  "value" : 11220
               },
               "duration" : {
                  "text" : "16 mins",
                  "value" : 967
               },
               "status" : "OK"
            },
            {
               "distance" : {
                  "text" : "4.7 mi",
                  "value" : 7531
               },
               "duration" : {
                  "text" : "13 mins",
                  "value" : 750
               },
               "status" : "OK"
            },
            {
               "distance" : {
                  "text" : "2.2 mi",
                  "value" : 3490
               },
               "duration" : {
                  "text" : "8 mins",
                  "value" : 455
               },
               "status" : "OK"
            },
            {
               "distance" : {
                  "text" : "1.2 mi",
                  "value" : 1889
               },
               "duration" : {
                  "text" : "4 mins",
                  "value" : 212
               },
               "status" : "OK"
            }
         ]
      }
   ],
   "status" : "OK"
}
