{
   "destination_addresses" : [
      "967 400 E, Seymour, IN 47274, USA",
      "1072 N County Rd 600 E, Seymour, IN 47274, USA",
      "1000 Hwy 11, Seymour, IN 47274, USA",
      "1009 N County Rd 950 E, Seymour, IN 47274, USA",
      "900 US-31, Seymour, IN 47274, USA",
      "5513-5951 900 W, Commiskey, IN 47227, USA",
      "4040 US-50, Seymour, IN 47274, USA",
      "2643-3999 N County Rd 600 E, Seymour, IN 47274, USA",
      "3018 Hwy 11, Seymour, IN 47274, USA",
      "9882 E 300 N, Seymour, IN 47274, USA",
      "2861-2989 US-31, Seymour, IN 47274, USA",
      "4045 S County Rd 900 W, Seymour, IN 47274, USA",
      "N County Rd 400 E, Seymour, IN 47274, USA",
      "6000 E County Rd 525 N, Seymour, IN 47274, USA",
      "335 S Walnut St, Seymour, IN 47274, USA",
      "1900 E Block Tipton St, Seymour, IN 47274, USA",
      "11298-11000 E County Rd 500 N, Seymour, IN 47274, USA",
      "W County Rd 200 S, Seymour, IN 47274, USA",
      "7248-7028 N County Rd 400 E, Seymour, IN 47274, USA",
      "6401-7999 S County Rd 550 E, Seymour, IN 47274, USA",
      "300 Enos Rd, Seymour, IN 47274, USA",
      "9942 E County Rd 700 N, Seymour, IN 47274, USA"
   ],
   "origin_addresses" : [ "721 E Tipton St, Seymour, IN 47274, USA" ],
   "rows" : [
      {
         "elements" : [
            {
               "distance" : {
                  "text" : "7.2 mi",
                  "value" : 11587
               },
               "duration" : {
                  "text" : "12 mins",
                  "value" : 691
               },
               "status" : "OK"
            },
            {
               "distance" : {
                  "text" : "6.3 mi",
                  "value" : 10101
               },
               "duration" : {
                  "text" : "11 mins",
                  "value" : 639
               },
               "status" : "OK"
            },
            {
               "distance" : {
                  "text" : "4.8 mi",
                  "value" : 7668
               },
               "duration" : {
                  "text" : "10 mins",
                  "value" : 590
               },
               "status" : "OK"
            },
            {
               "distance" : {
                  "text" : "5.7 mi",
                  "value" : 9177
               },
               "duration" : {
                  "text" : "12 mins",
                  "value" : 746
               },
               "status" : "OK"
            },
            {
               "distance" : {
                  "text" : "6.4 mi",
                  "value" : 10282
               },
               "duration" : {
                  "text" : "9 mins",
                  "value" : 525
               },
               "status" : "OK"
            },
            {
               "distance" : {
                  "text" : "10.8 mi",
                  "value" : 17332
               },
               "duration" : {
                  "text" : "18 mins",
                  "value" : 1075
               },
               "status" : "OK"
            },
            {
               "distance" : {
                  "text" : "5.3 mi",
                  "value" : 8557
               },
               "duration" : {
                  "text" : "9 mins",
                  "value" : 542
               },
               "status" : "OK"
            },
            {
               "distance" : {
                  "text" : "4.1 mi",
                  "value" : 6588
               },
               "duration" : {
                  "text" : "8 mins",
                  "value" : 465
               },
               "status" : "OK"
            },
            {
               "distance" : {
                  "text" : "2.9 mi",
                  "value" : 4695
               },
               "duration" : {
                  "text" : "7 mins",
                  "value" : 399
               },
               "status" : "OK"
            },
            {
               "distance" : {
                  "text" : "4.0 mi",
                  "value" : 6369
               },
               "duration" : {
                  "text" : "9 mins",
                  "value" : 518
               },
               "status" : "OK"
            },
            {
               "distance" : {
                  "text" : "9.7 mi",
                  "value" : 15576
               },
               "duration" : {
                  "text" : "26 mins",
                  "value" : 1538
               },
               "status" : "OK"
            },
            {
               "distance" : {
                  "text" : "8.8 mi",
                  "value" : 14125
               },
               "duration" : {
                  "text" : "14 mins",
                  "value" : 867
               },
               "status" : "OK"
            },
            {
               "distance" : {
                  "text" : "5.4 mi",
                  "value" : 8618
               },
               "duration" : {
                  "text" : "12 mins",
                  "value" : 696
               },
               "status" : "OK"
            },
            {
               "distance" : {
                  "text" : "3.0 mi",
                  "value" : 4827
               },
               "duration" : {
                  "text" : "8 mins",
                  "value" : 457
               },
               "status" : "OK"
            },
            {
               "distance" : {
                  "text" : "0.9 mi",
                  "value" : 1477
               },
               "duration" : {
                  "text" : "3 mins",
                  "value" : 199
               },
               "status" : "OK"
            },
            {
               "distance" : {
                  "text" : "1.9 mi",
                  "value" : 2985
               },
               "duration" : {
                  "text" : "7 mins",
                  "value" : 439
               },
               "status" : "OK"
            },
            {
               "distance" : {
                  "text" : "3.6 mi",
                  "value" : 5816
               },
               "duration" : {
                  "text" : "10 mins",
                  "value" : 620
               },
               "status" : "OK"
            },
            {
               "distance" : {
                  "text" : "6.9 mi",
                  "value" : 11181
               },
               "duration" : {
                  "text" : "12 mins",
                  "value" : 722
               },
               "status" : "OK"
            },
            {
               "distance" : {
                  "text" : "6.9 mi",
                  "value" : 11026
               },
               "duration" : {
                  "text" : "14 mins",
                  "value" : 850
               },
               "status" : "OK"
            },
            {
               "distance" : {
                  "text" : "6.0 mi",
                  "value" : 9733
               },
               "duration" : {
                  "text" : "12 mins",
                  "value" : 736
               },
               "status" : "OK"
            },
            {
               "distance" : {
                  "text" : "2.4 mi",
                  "value" : 3894
               },
               "duration" : {
                  "text" : "6 mins",
                  "value" : 383
               },
               "status" : "OK"
            },
            {
               "distance" : {
                  "text" : "3.3 mi",
                  "value" : 5289
               },
               "duration" : {
                  "text" : "8 mins",
                  "value" : 457
               },
               "status" : "OK"
            }
         ]
      }
   ],
   "status" : "OK"
}
