{
   "destination_addresses" : [
      "7341 E Stop 11 Rd, Indianapolis, IN 46259, USA",
      "1319 W Edgewood Ave, Indianapolis, IN 46217, USA",
      "541 E Edgewood Ave, Indianapolis, IN 46227, USA",
      "3010 Locust Dr, Indianapolis, IN 46227, USA",
      "6157 Arctic Cir, Indianapolis, IN 46237, USA",
      "6291 Five Points Rd, Indianapolis, IN 46259, USA"
   ],
   "origin_addresses" : [ "186 Surina Way, Greenwood, IN 46143, USA" ],
   "rows" : [
      {
         "elements" : [
            {
               "distance" : {
                  "text" : "6.0 mi",
                  "value" : 9659
               },
               "duration" : {
                  "text" : "14 mins",
                  "value" : 815
               },
               "status" : "OK"
            },
            {
               "distance" : {
                  "text" : "7.7 mi",
                  "value" : 12393
               },
               "duration" : {
                  "text" : "18 mins",
                  "value" : 1101
               },
               "status" : "OK"
            },
            {
               "distance" : {
                  "text" : "6.0 mi",
                  "value" : 9636
               },
               "duration" : {
                  "text" : "14 mins",
                  "value" : 838
               },
               "status" : "OK"
            },
            {
               "distance" : {
                  "text" : "5.5 mi",
                  "value" : 8828
               },
               "duration" : {
                  "text" : "13 mins",
                  "value" : 772
               },
               "status" : "OK"
            },
            {
               "distance" : {
                  "text" : "7.2 mi",
                  "value" : 11530
               },
               "duration" : {
                  "text" : "15 mins",
                  "value" : 913
               },
               "status" : "OK"
            },
            {
               "distance" : {
                  "text" : "8.0 mi",
                  "value" : 12821
               },
               "duration" : {
                  "text" : "17 mins",
                  "value" : 1042
               },
               "status" : "OK"
            }
         ]
      }
   ],
   "status" : "OK"
}
