{
   "destination_addresses" : [
      "7482 County Rd 325 N, Larwill, IN 46764, USA",
      "999-237 N 300 E, Warsaw, IN 46582, USA",
      "4991-5363 E Old Rd 30, Pierceton, IN 46562, USA",
      "7068-6838 Lincoln Hwy, Pierceton, IN 46562, USA",
      "322 N 900 E, Pierceton, IN 46562, USA",
      "Ulrich Dr, Larwill, IN 46764, USA"
   ],
   "origin_addresses" : [ "205 S 1st St, Pierceton, IN 46562, USA" ],
   "rows" : [
      {
         "elements" : [
            {
               "distance" : {
                  "text" : "4.9 mi",
                  "value" : 7949
               },
               "duration" : {
                  "text" : "9 mins",
                  "value" : 553
               },
               "status" : "OK"
            },
            {
               "distance" : {
                  "text" : "6.2 mi",
                  "value" : 9961
               },
               "duration" : {
                  "text" : "9 mins",
                  "value" : 524
               },
               "status" : "OK"
            },
            {
               "distance" : {
                  "text" : "5.0 mi",
                  "value" : 8074
               },
               "duration" : {
                  "text" : "7 mins",
                  "value" : 425
               },
               "status" : "OK"
            },
            {
               "distance" : {
                  "text" : "3.1 mi",
                  "value" : 4980
               },
               "duration" : {
                  "text" : "5 mins",
                  "value" : 300
               },
               "status" : "OK"
            },
            {
               "distance" : {
                  "text" : "4.6 mi",
                  "value" : 7363
               },
               "duration" : {
                  "text" : "7 mins",
                  "value" : 404
               },
               "status" : "OK"
            },
            {
               "distance" : {
                  "text" : "7.2 mi",
                  "value" : 11617
               },
               "duration" : {
                  "text" : "11 mins",
                  "value" : 652
               },
               "status" : "OK"
            }
         ]
      }
   ],
   "status" : "OK"
}
