{
   "destination_addresses" : [
      "4701-5399 S Meridian Line Rd, Cloverdale, IN 46120, USA",
      "2202 Deer Creek Dr, Greencastle, IN 46135, USA",
      "7760 W County Rd 275 S, Greencastle, IN 46135, USA",
      "5862 W County Rd 275 S, Greencastle, IN 46135, USA",
      "3921 W Co Rd 300 S, Greencastle, IN 46135, USA",
      "1721 W Co Rd 300 S, Greencastle, IN 46135, USA",
      "1556 S Bloomington St, Greencastle, IN 46135, USA",
      "E CR-225 S, Greencastle, IN 46135, USA",
      "7755-7823 W County Rd 75 S, Greencastle, IN 46135, USA",
      "5947 W County Rd 100 S, Greencastle, IN 46135, USA",
      "3400-3982 W County Rd 125 S, Greencastle, IN 46135, USA",
      "1886-1396 W Co Rd 100 S, Greencastle, IN 46135, USA",
      "1038 Shadowlawn Ave, Greencastle, IN 46135, USA",
      "People Pathways, Fillmore, IN 46128, USA"
   ],
   "origin_addresses" : [ "1927 US-40, Greencastle, IN 46135, USA" ],
   "rows" : [
      {
         "elements" : [
            {
               "distance" : {
                  "text" : "3.5 mi",
                  "value" : 5625
               },
               "duration" : {
                  "text" : "7 mins",
                  "value" : 408
               },
               "status" : "OK"
            },
            {
               "distance" : {
                  "text" : "5.1 mi",
                  "value" : 8203
               },
               "duration" : {
                  "text" : "10 mins",
                  "value" : 571
               },
               "status" : "OK"
            },
            {
               "distance" : {
                  "text" : "11.7 mi",
                  "value" : 18878
               },
               "duration" : {
                  "text" : "18 mins",
                  "value" : 1079
               },
               "status" : "OK"
            },
            {
               "distance" : {
                  "text" : "8.0 mi",
                  "value" : 12877
               },
               "duration" : {
                  "text" : "15 mins",
                  "value" : 913
               },
               "status" : "OK"
            },
            {
               "distance" : {
                  "text" : "5.3 mi",
                  "value" : 8553
               },
               "duration" : {
                  "text" : "10 mins",
                  "value" : 607
               },
               "status" : "OK"
            },
            {
               "distance" : {
                  "text" : "4.9 mi",
                  "value" : 7953
               },
               "duration" : {
                  "text" : "9 mins",
                  "value" : 519
               },
               "status" : "OK"
            },
            {
               "distance" : {
                  "text" : "6.8 mi",
                  "value" : 10867
               },
               "duration" : {
                  "text" : "9 mins",
                  "value" : 531
               },
               "status" : "OK"
            },
            {
               "distance" : {
                  "text" : "7.8 mi",
                  "value" : 12543
               },
               "duration" : {
                  "text" : "11 mins",
                  "value" : 651
               },
               "status" : "OK"
            },
            {
               "distance" : {
                  "text" : "15.3 mi",
                  "value" : 24699
               },
               "duration" : {
                  "text" : "20 mins",
                  "value" : 1196
               },
               "status" : "OK"
            },
            {
               "distance" : {
                  "text" : "8.9 mi",
                  "value" : 14263
               },
               "duration" : {
                  "text" : "18 mins",
                  "value" : 1067
               },
               "status" : "OK"
            },
            {
               "distance" : {
                  "text" : "7.1 mi",
                  "value" : 11503
               },
               "duration" : {
                  "text" : "15 mins",
                  "value" : 886
               },
               "status" : "OK"
            },
            {
               "distance" : {
                  "text" : "8.0 mi",
                  "value" : 12921
               },
               "duration" : {
                  "text" : "14 mins",
                  "value" : 866
               },
               "status" : "OK"
            },
            {
               "distance" : {
                  "text" : "8.2 mi",
                  "value" : 13216
               },
               "duration" : {
                  "text" : "16 mins",
                  "value" : 952
               },
               "status" : "OK"
            },
            {
               "distance" : {
                  "text" : "9.8 mi",
                  "value" : 15818
               },
               "duration" : {
                  "text" : "16 mins",
                  "value" : 956
               },
               "status" : "OK"
            }
         ]
      }
   ],
   "status" : "OK"
}
